Metadata-Version: 1.2
Name: pyintersection
Version: 1.1
Summary: Pyintersection package
Home-page: https://github.com/suspiciousFruit/pyintersection
License: UNKNOWN
Platform: UNKNOWN
Requires-Python: >=3.7
